hypyspectral/__init__.py
hypyspectral/hypyspectral.py
hypyspectral/algorithms/__init__.py
hypyspectral/algorithms/band_selection.py
hypyspectral/algorithms/clustering.py
hypyspectral/algorithms/detectors.py
hypyspectral/algorithms/dimensionality_reduction.py
hypyspectral/algorithms/vegetation_indices.py
hypyspectral/io/__init__.py
hypyspectral/io/asd.py
hypyspectral/io/envi.py
hypyspectral/io/generic.py
hypyspectral/io/geotiff.py
hypyspectral/tests/__init__.py
hypyspectral/utils/__init__.py
hypyspectral/utils/utils.py
hypyspectral/visualisation/__init__.py
hypyspectral/visualisation/hsi2rgb.py
hypyspectral/visualisation/visualise_hsi.py
hypyspectral-0.0.2.dist-info/METADATA
hypyspectral-0.0.2.dist-info/WHEEL
hypyspectral-0.0.2.dist-info/top_level.txt
hypyspectral-0.0.2.dist-info/RECORD
